smartmoneyconcepts/__init__.py
smartmoneyconcepts/smc.py
smartmoneyconcepts-0.0.24.dist-info/WHEEL
smartmoneyconcepts-0.0.24.dist-info/LICENSE
smartmoneyconcepts-0.0.24.dist-info/METADATA
smartmoneyconcepts-0.0.24.dist-info/RECORD
